MANIFEST.in
README.md
setup.py
ibt/__init__.py
ibt/__main__.py
ibt/command.py
ibt/container_util.py
ibt/context.py
ibt/destroy_command.py
ibt/docker_util.py
ibt/help_command.py
ibt/info_command.py
ibt/project.py
ibt/run_command.py
ibt/script_command.py
ibt/shell_command.py
ibt/tracing.py
ibt/up_command.py
ibt/util.py
ibt.egg-info/PKG-INFO
ibt.egg-info/SOURCES.txt
ibt.egg-info/dependency_links.txt
ibt.egg-info/entry_points.txt
ibt.egg-info/not-zip-safe
ibt.egg-info/requires.txt
ibt.egg-info/top_level.txt