Metadata-Version: 1.1
Name: ibt
Version: 0.6
Summary: Simple wrappers around Docker etc. for fully isolated build environments
Home-page: https://github.com/rcook/ibt
Author: Richard Cook
Author-email: rcook@rcook.org
License: MIT
Platform: UNKNOWN
Classifier: Development Status :: 3 - Alpha
Classifier: License :: OSI Approved :: MIT License
Classifier: Programming Language :: Python :: 2.7
